nmrglue/__init__.py
nmrglue/analysis/__init__.py
nmrglue/analysis/analysisbase.py
nmrglue/analysis/helpers.py
nmrglue/analysis/integration.py
nmrglue/analysis/leastsqbound.py
nmrglue/analysis/linesh.py
nmrglue/analysis/lineshapes1d.py
nmrglue/analysis/peakpick.py
nmrglue/analysis/segmentation.py
nmrglue/analysis/tests/test_analysis_integration.py
nmrglue/analysis/tests/test_analysis_linesh.py
nmrglue/fileio/__init__.py
nmrglue/fileio/bruker.py
nmrglue/fileio/convert.py
nmrglue/fileio/fileiobase.py
nmrglue/fileio/glue.py
nmrglue/fileio/jcampdx.py
nmrglue/fileio/nmrml.py
nmrglue/fileio/pipe.py
nmrglue/fileio/rnmrtk.py
nmrglue/fileio/simpson.py
nmrglue/fileio/sparky.py
nmrglue/fileio/spinsolve.py
nmrglue/fileio/table.py
nmrglue/fileio/tecmag.py
nmrglue/fileio/varian.py
nmrglue/fileio/tests/test_bruker.py
nmrglue/fileio/tests/test_fileiobase.py
nmrglue/fileio/tests/test_pipe.py
nmrglue/fileio/tests/bruker_test_data/1/acqus
nmrglue/fileio/tests/bruker_test_data/1/pdata/1/1r
nmrglue/fileio/tests/bruker_test_data/1/pdata/1/procs
nmrglue/fileio/tests/data/nmrpipe_1d_ext.fid
nmrglue/fileio/tests/data/nmrpipe_1d_freq.fid
nmrglue/fileio/tests/data/nmrpipe_1d_time.fid
nmrglue/fileio/tests/data/nmrpipe_2d_freq.ft2
nmrglue/fileio/tests/data/nmrpipe_2d_freq_tp.ft2
nmrglue/fileio/tests/data/nmrpipe_2d_time.fid
nmrglue/fileio/tests/data/nmrpipe_2d_time_tp.fid
nmrglue/fileio/tests/data/nmrpipe_3d_freq.ft3
nmrglue/fileio/tests/data/nmrpipe_3d_time.fid
nmrglue/fileio/tests/data/nmrpipe_4d_freq.ft4
nmrglue/fileio/tests/data/nmrpipe_4d_time.fid
nmrglue/fileio/tests/data/test.tab
nmrglue/fileio/tests/data/nmrpipe_3d_freq.dir/nmrpipe_3d_freq_001.ft3
nmrglue/fileio/tests/data/nmrpipe_3d_freq.dir/nmrpipe_3d_freq_002.ft3
nmrglue/fileio/tests/data/nmrpipe_3d_time.dir/nmrpipe_3d_time_001.fid
nmrglue/fileio/tests/data/nmrpipe_3d_time.dir/nmrpipe_3d_time_002.fid
nmrglue/fileio/tests/data/nmrpipe_3d_time.dir/nmrpipe_3d_time_003.fid
nmrglue-0.11.dist-info/LICENSE.txt
nmrglue-0.11.dist-info/METADATA
nmrglue-0.11.dist-info/WHEEL
nmrglue-0.11.dist-info/top_level.txt
nmrglue-0.11.dist-info/RECORD
